snosample/__init__.py
snosample/assertions.py
snosample/logging.py
snosample/multi.py
snosample/testing.py
snosample-3.5.2.dist-info/METADATA
snosample-3.5.2.dist-info/WHEEL
snosample-3.5.2.dist-info/RECORD
