Metadata-Version: 2.1
Name: SnoSample
Version: 3.5.2
Summary: Simplified tools for Python projects.
Home-page: https://dev.azure.com/snomax/SnoSample
License: MIT
Author: Max Snoodijk
Author-email: max_snoodijk@live.nl
Maintainer: Max Snoodijk
Maintainer-email: max_snoodijk@live.nl
Requires-Python: >=3.9,<4.0
Classifier: License :: OSI Approved :: MIT License
Classifier: Programming Language :: Python :: 3
Classifier: Programming Language :: Python :: 3.9
Classifier: Programming Language :: Python :: 3.10
Classifier: Programming Language :: Python :: 3.11
Classifier: Programming Language :: Python :: 3.12
Requires-Dist: numpy (>=1.26,<2.0)
Project-URL: Repository, https://dev.azure.com/snomax/SnoSample
